ya_payment/__init__.py
ya_payment/api_client.py
ya_payment/configuration.py
ya_payment/exceptions.py
ya_payment/rest.py
ya_payment/api/__init__.py
ya_payment/api/provider_api.py
ya_payment/api/requestor_api.py
ya_payment/models/__init__.py
ya_payment/models/acceptance.py
ya_payment/models/activity_payment.py
ya_payment/models/agreement_payment.py
ya_payment/models/allocation.py
ya_payment/models/debit_note.py
ya_payment/models/debit_note_event.py
ya_payment/models/error_message.py
ya_payment/models/event_type.py
ya_payment/models/invoice.py
ya_payment/models/invoice_event.py
ya_payment/models/invoice_status.py
ya_payment/models/payment.py
ya_payment/models/rejection.py
ya_payment/models/rejection_reason.py
ya_client_payment-0.1.0.dist-info/METADATA
ya_client_payment-0.1.0.dist-info/WHEEL
ya_client_payment-0.1.0.dist-info/top_level.txt
ya_client_payment-0.1.0.dist-info/RECORD
